staticvectors/__init__.py
staticvectors/model.py
staticvectors/tokenizer.py
staticvectors/train.py
staticvectors/xhash.py
staticvectors/converter/__init__.py
staticvectors/converter/base.py
staticvectors/converter/ftext.py
staticvectors/converter/svectors.py
staticvectors/converter/text.py
staticvectors/loss/__init__.py
staticvectors/loss/base.py
staticvectors/loss/factory.py
staticvectors/loss/hsoftmax.py
staticvectors/loss/softmax.py
staticvectors/storage/__init__.py
staticvectors/storage/base.py
staticvectors/storage/database.py
staticvectors/storage/factory.py
staticvectors/storage/retriever.py
staticvectors/storage/tensors.py
staticvectors-0.2.0.dist-info/LICENSE
staticvectors-0.2.0.dist-info/METADATA
staticvectors-0.2.0.dist-info/WHEEL
staticvectors-0.2.0.dist-info/top_level.txt
staticvectors-0.2.0.dist-info/RECORD
