Metadata-Version: 2.1
Name: staticvectors
Version: 0.2.0
Summary: Work with static vector models
Home-page: https://github.com/neuml/staticvectors
Author: NeuML
License: Apache 2.0: http://www.apache.org/licenses/LICENSE-2.0
Project-URL: Documentation, https://github.com/neuml/staticvectors
Project-URL: Issue Tracker, https://github.com/neuml/staticvectors/issues
Project-URL: Source Code, https://github.com/neuml/staticvectors
Keywords: search embedding machine-learning nlp
Classifier: License :: OSI Approved :: Apache Software License
Classifier: Operating System :: OS Independent
Classifier: Programming Language :: Python :: 3
Classifier: Topic :: Scientific/Engineering :: Artificial Intelligence
Classifier: Topic :: Software Development
Classifier: Topic :: Text Processing :: Indexing
Classifier: Topic :: Utilities
Requires-Python: >=3.9
License-File: LICENSE
Requires-Dist: huggingface-hub (>=0.19.0)
Requires-Dist: numpy (>=1.18.4)
Requires-Dist: safetensors (>=0.4.5)
Requires-Dist: tqdm (>=4.48.0)
Provides-Extra: train
Requires-Dist: fasttext-wheel (>=0.9.2) ; extra == 'train'
Requires-Dist: nanopq (>=0.2.1) ; extra == 'train'
